racing_data/__init__.py
racing_data/constants.py
racing_data/entity.py
racing_data/horse.py
racing_data/jockey.py
racing_data/meet.py
racing_data/performance.py
racing_data/performance_list.py
racing_data/provider.py
racing_data/race.py
racing_data/runner.py
racing_data/trainer.py
racing_data-1.0.0b11.dist-info/DESCRIPTION.rst
racing_data-1.0.0b11.dist-info/METADATA
racing_data-1.0.0b11.dist-info/RECORD
racing_data-1.0.0b11.dist-info/WHEEL
racing_data-1.0.0b11.dist-info/entry_points.txt
racing_data-1.0.0b11.dist-info/metadata.json
racing_data-1.0.0b11.dist-info/top_level.txt
