Metadata-Version: 2.0
Name: racing-data
Version: 1.0.0b11
Summary: Python horse racing class library
Home-page: https://github.com/justjasongreen/racing_data
Author: Jason Green
Author-email: justjasongreen@gmail.com
License: MIT
Keywords: horse racing class library
Platform: UNKNOWN
Classifier: Development Status :: 4 - Beta
Classifier: Intended Audience :: Developers
Classifier: License :: OSI Approved :: MIT License
Classifier: Natural Language :: English
Classifier: Operating System :: OS Independent
Classifier: Programming Language :: Python :: 2.7
Classifier: Programming Language :: Python :: 3.5
Classifier: Topic :: Software Development :: Libraries :: Python Modules
Requires-Dist: pytz
Requires-Dist: tzlocal
Provides-Extra: dev
Requires-Dist: bumpversion; extra == 'dev'
Requires-Dist: check-manifest; extra == 'dev'
Provides-Extra: test
Requires-Dist: tox; extra == 'test'
